{
  "containerDefinitions": [
    {
      "name": "today-lunch-task02",
      "image": "448648424519.dkr.ecr.ap-northeast-2.amazonaws.com/today-lunch-ecr-repo",
      "cpu": 0,
      "memory": 512,
      "memoryReservation": 512,
      "portMappings": [
        {
          "containerPort": 8080,
          "hostPort": 0,
          "protocol": "tcp"
        }
      ],
      "essential": true,
      "environment": [],
      "mountPoints": [],
      "volumesFrom": []
    }
  ],
  "family": "today-lunch-task02",
  "executionRoleArn": "arn:aws:iam::448648424519:role/ecsTaskExecutionRole",
  "revision": 1,
  "volumes": [],
  "status": "ACTIVE",
  "placementConstraints": [],
  "requiresCompatibilities": ["EC2"],
  "tags": []
}
